oscapify/__init__.py
oscapify/cache.py
oscapify/cli.py
oscapify/core.py
oscapify/exceptions.py
oscapify/models.py
oscapify/validators.py
oscapify-0.1.0.dist-info/LICENSE
oscapify-0.1.0.dist-info/METADATA
oscapify-0.1.0.dist-info/WHEEL
oscapify-0.1.0.dist-info/entry_points.txt
oscapify-0.1.0.dist-info/RECORD
