Metadata-Version: 2.3
Name: oscapify
Version: 0.1.0
Summary: A robust tool for converting scientific literature CSV files to OSCAP-compatible format
License: MIT
Keywords: oscap,scientific-literature,csv,converter
Author: Jordan R. Willis
Author-email: jwillis0720@gmail.com
Requires-Python: >=3.8,<4.0
Classifier: Development Status :: 4 - Beta
Classifier: Intended Audience :: Science/Research
Classifier: License :: OSI Approved :: MIT License
Classifier: Programming Language :: Python :: 3
Classifier: Programming Language :: Python :: 3.8
Classifier: Programming Language :: Python :: 3.9
Classifier: Programming Language :: Python :: 3.10
Classifier: Programming Language :: Python :: 3.11
Classifier: Programming Language :: Python :: 3.12
Classifier: Programming Language :: Python :: 3.13
Classifier: Topic :: Scientific/Engineering
Classifier: Topic :: Software Development :: Libraries :: Python Modules
Requires-Dist: click (>=8.0,<9.0)
Requires-Dist: pandas (>=1.5.0)
Requires-Dist: platformdirs (>=2.0.0,<3.0.0)
Requires-Dist: pydantic (>=2.0.0,<3.0.0)
Requires-Dist: requests (>=2.25.0,<3.0.0)
Project-URL: Documentation, https://github.com/yourusername/oscapify
Project-URL: Homepage, https://github.com/yourusername/oscapify
Project-URL: Issues, https://github.com/yourusername/oscapify/issues
Project-URL: Repository, https://github.com/yourusername/oscapify
